cursoHack/__init__.py
cursoHack/courses.py
cursoHack/utils.py
cursohacker-0.1.7.dist-info/METADATA
cursohacker-0.1.7.dist-info/WHEEL
cursohacker-0.1.7.dist-info/top_level.txt
cursohacker-0.1.7.dist-info/RECORD
