Metadata-Version: 2.4
Name: CursoHacker
Version: 0.1.7
Summary: Una biblioteca para consultar cursos de hack4u
Home-page: https://hack4u.io
Author: Sergio López
Dynamic: author
Dynamic: description
Dynamic: description-content-type
Dynamic: home-page
Dynamic: summary
